cir_duplicate_detector/__init__.py
cir_duplicate_detector/pdq_dup_detect_algorithms/bk_tree.py
cir_duplicate_detector/pdq_dup_detect_algorithms/naive_duplicate_detector.py
cir_duplicate_detector/pdq_dup_detect_algorithms/utils.py
cir_duplicate_detector/pdq_hash.py
cir_duplicate_detector/url.py
cir_duplicate_detector-0.1.8.dist-info/LICENSE
cir_duplicate_detector-0.1.8.dist-info/METADATA
cir_duplicate_detector-0.1.8.dist-info/WHEEL
cir_duplicate_detector-0.1.8.dist-info/RECORD
