Metadata-Version: 2.1
Name: cir-duplicate-detector
Version: 0.1.8
Summary: PDQ hash and URL duplicate detector. Developed by Sam Sweere from BigData Repulic as part of their Social Good Initiaive.
Home-page: https://github.com/Centre-for-Information-Resilience/cir-duplicate-detector
License: BSD-3-Clause
Author: Sam Sweere
Author-email: samsweere@gmail.com
Requires-Python: >=3.10,<3.12
Classifier: License :: OSI Approved :: BSD License
Classifier: Programming Language :: Python :: 3
Classifier: Programming Language :: Python :: 3.10
Classifier: Programming Language :: Python :: 3.11
Requires-Dist: bitarray (>=2.1,<3.0)
Requires-Dist: pandas (>=1.3)
Requires-Dist: pdqhash (>=0.2.5,<0.3.0)
Requires-Dist: pybktree (>=1.1,<2.0)
Requires-Dist: rapidfuzz (>=3,<4)
Requires-Dist: tqdm (>=4,<5)
Project-URL: Repository, https://github.com/Centre-for-Information-Resilience/cir-duplicate-detector
